{"chrome://browser/content/browser.xhtml":{"main-window":{"screenX":"0","screenY":"0","width":"963","height":"1044","sizemode":"maximized"},"vertical-tabs":{"collapsed":"false"},"TabsToolbar":{"collapsed":"true"},"sidebar-title":{"value":""}},"chrome://browser/content/places/places.xhtml":{"placesContentTags":{"ordinal":"3"},"placesContentUrl":{"ordinal":"5"},"placesContentDate":{"ordinal":"7"},"placesContentVisitCount":{"ordinal":"9","sortDirection":"-moz-missing\n"},"placesContentDateAdded":{"ordinal":"11"},"placesContentLastModified":{"ordinal":"13"},"places":{"screenX":"0","screenY":"0","width":"1308","height":"750","sizemode":"normal"},"place:CqewroxEONFH0b8ILWSXYA==":{"open":"true"},"place:OmHfAW8r3JtHUJDITYXmXg==":{"open":"true"}},"chrome://browser/content/setDesktopBackground.xhtml":{"menuPosition":{"value":"CENTER"}},"chrome://global/content/pictureinpicture/player.xhtml":{"picture-in-picture":{"left":"0","top":"0","width":"853","height":"480"}}}